lqq/__init__.py
lqq/zxq/__init__.py
lqq/zxq/message.py
hhl_lqq-0.1.dist-info/METADATA
hhl_lqq-0.1.dist-info/WHEEL
hhl_lqq-0.1.dist-info/top_level.txt
hhl_lqq-0.1.dist-info/RECORD
