Metadata-Version: 2.1
Name: hhl-lqq
Version: 0.1
Summary: 黄慧琳 梁琪琪 钟香琴
Author: hhl
License: UNKNOWN
Platform: UNKNOWN
